src/dashboard-listener-raku/WebListener.py
src/dashboard-listener-raku/__init__.py
dashboard_listener_raku-0.0.1.dist-info/METADATA
dashboard_listener_raku-0.0.1.dist-info/WHEEL
dashboard_listener_raku-0.0.1.dist-info/licenses/LICENSE
dashboard_listener_raku-0.0.1.dist-info/RECORD
