Metadata-Version: 2.1
Name: dashboard-listener-raku
Version: 0.0.1
Summary: Web Listener code for Robot Framework
Author-email: Guilherme Santana <ts-guilherme.santana@rakuten.com>
License-File: LICENSE
Classifier: License :: OSI Approved :: MIT License
Classifier: Operating System :: OS Independent
Classifier: Programming Language :: Python :: 3
Requires-Python: >=3.7
